littleIndian/__init__.py
littleIndian/littleindian.py
littleIndian-1.0.5.dist-info/METADATA
littleIndian-1.0.5.dist-info/RECORD
littleIndian-1.0.5.dist-info/WHEEL
littleIndian-1.0.5.dist-info/top_level.txt
