Metadata-Version: 2.1
Name: littleIndian
Version: 1.0.5
Summary: A demo package to print the lyrics of the Little Indian song
Home-page: https://github.com/pythoslabs/littleIndian
Author: Pythos Labs
Author-email: pythoslabs@gmail.com
License: MIT
Platform: UNKNOWN
Classifier: License :: OSI Approved :: MIT License
Classifier: Programming Language :: Python :: 3
Classifier: Programming Language :: Python :: 3.7
